pycodemap/__main__.py
pycodemap/analyzer.py
pycodemap/formatter.py
pycodemap-1.0.6.dist-info/LICENSE
pycodemap-1.0.6.dist-info/METADATA
pycodemap-1.0.6.dist-info/WHEEL
pycodemap-1.0.6.dist-info/entry_points.txt
pycodemap-1.0.6.dist-info/top_level.txt
pycodemap-1.0.6.dist-info/RECORD
