Metadata-Version: 2.1
Name: pycodemap
Version: 1.0.6
Summary: A CLI tool for extracting and outlining the structure of Python code.
Author: Artyom Prokhorov
License: MIT
Project-URL: Repository, https://github.com/your_username/PyCodeMap
Classifier: Programming Language :: Python :: 3
Classifier: License :: OSI Approved :: MIT License
Classifier: Operating System :: OS Independent
Requires-Python: >=3.6
License-File: LICENSE
